__init__.py
sklearn_embeddings.py
sklearn_embeddings-0.1.3.dist-info/licenses/LICENSE
sklearn_embeddings-0.1.3.dist-info/METADATA
sklearn_embeddings-0.1.3.dist-info/WHEEL
sklearn_embeddings-0.1.3.dist-info/top_level.txt
sklearn_embeddings-0.1.3.dist-info/RECORD
