Metadata-Version: 2.4
Name: sklearn-embeddings
Version: 0.1.3
Summary: Sentence-Transformer embeddings for scikit-learn
License: MIT
Requires-Python: >=3.8
License-File: LICENSE
Requires-Dist: scikit-learn>=1.0.0
Requires-Dist: sentence-transformers>=2.0.0
Provides-Extra: dev
Requires-Dist: pytest>=8.3.0; extra == "dev"
Requires-Dist: black; extra == "dev"
Requires-Dist: flake8; extra == "dev"
Requires-Dist: twine; extra == "dev"
Requires-Dist: build; extra == "dev"
Requires-Dist: mypy; extra == "dev"
Dynamic: license-file
